specular/__init__.py
specular/calculation.py
specular/jax/__init__.py
specular/jax/calculation.py
specular/jax/optimization/__init__.py
specular/jax/optimization/solver.py
specular/ode/__init__.py
specular/ode/result.py
specular/ode/solver.py
specular/optimization/__init__.py
specular/optimization/classical_solver.py
specular/optimization/result.py
specular/optimization/solver.py
specular/optimization/step_size.py
specular_differentiation-1.0.7.dist-info/licenses/LICENSE
specular_differentiation-1.0.7.dist-info/METADATA
specular_differentiation-1.0.7.dist-info/WHEEL
specular_differentiation-1.0.7.dist-info/top_level.txt
specular_differentiation-1.0.7.dist-info/RECORD
