Metadata-Version: 2.4
Name: specular-differentiation
Version: 1.0.7
Summary: Specular differentiation in normed vector spaces and its applications
Author-email: Kiyuob Jung <kyjung@msu.edu>
License: MIT License
Project-URL: Homepage, https://github.com/kyjung2357/specular-differentiation
Project-URL: Bug Tracker, https://github.com/kyjung2357/specular-differentiation/issues
Classifier: Programming Language :: Python :: 3
Classifier: Programming Language :: Python :: 3.11
Classifier: Intended Audience :: Science/Research
Classifier: License :: OSI Approved :: MIT License
Classifier: Operating System :: OS Independent
Classifier: Topic :: Scientific/Engineering :: Mathematics
Requires-Python: >=3.11
License-File: LICENSE
Requires-Dist: numpy>=2.4.0
Requires-Dist: ipython>=8.12.3
Requires-Dist: matplotlib>=3.10.8
Requires-Dist: pandas>=2.3.3
Requires-Dist: tqdm>=4.67.1
Provides-Extra: jax
Requires-Dist: jax>=0.4; extra == "jax"
Requires-Dist: jaxlib>=0.4; extra == "jax"
Provides-Extra: dev
Requires-Dist: specular-differentiation[jax]; extra == "dev"
Requires-Dist: pytest>=7.0; extra == "dev"
Requires-Dist: scipy>=1.10.0; extra == "dev"
Requires-Dist: torch>=2.0.0; extra == "dev"
Dynamic: description
Dynamic: description-content-type
Dynamic: license-file
